openwillis/transcribe/__init__.py
openwillis/transcribe/speech_separation_labels.py
openwillis/transcribe/speech_separation_nlabels.py
openwillis/transcribe/speech_transcribe_cloud.py
openwillis/transcribe/speech_transcribe_vosk.py
openwillis/transcribe/speech_transcribe_whisper.py
openwillis/transcribe/willisdiarize.py
openwillis/transcribe/willisdiarize_aws.py
openwillis/transcribe/commons/__init__.py
openwillis/transcribe/commons/common.py
openwillis/transcribe/commons/common_separation.py
openwillis/transcribe/config/speech.json
openwillis/transcribe/config/whisper_asr.json
openwillis/transcribe/util/__init__.py
openwillis/transcribe/util/diarization_utils.py
openwillis/transcribe/util/huggingface_utils.py
openwillis/transcribe/util/separation_util.py
openwillis/transcribe/util/transcribe_util.py
openwillis/transcribe/util/util.py
openwillis/transcribe/util/whisperx_util.py
openwillis_transcribe-1.1.0.dist-info/METADATA
openwillis_transcribe-1.1.0.dist-info/WHEEL
openwillis_transcribe-1.1.0.dist-info/top_level.txt
openwillis_transcribe-1.1.0.dist-info/RECORD
